ManipulaPy/__init__.py
ManipulaPy/control.py
ManipulaPy/cuda_kernels.py
ManipulaPy/dynamics.py
ManipulaPy/ik_helpers.py
ManipulaPy/kinematics.py
ManipulaPy/path_planning.py
ManipulaPy/perception.py
ManipulaPy/potential_field.py
ManipulaPy/sim.py
ManipulaPy/singularity.py
ManipulaPy/transformations.py
ManipulaPy/urdf_processor.py
ManipulaPy/utils.py
ManipulaPy/vision.py
ManipulaPy/ManipulaPy_data/MANIFEST.md
ManipulaPy/ManipulaPy_data/__init__.py
ManipulaPy/ManipulaPy_data/abb/irb2400.urdf
ManipulaPy/ManipulaPy_data/fanuc/lrmate200ib.urdf
ManipulaPy/ManipulaPy_data/fanuc/m16ib.urdf
ManipulaPy/ManipulaPy_data/fanuc_crx/crx10ia.urdf
ManipulaPy/ManipulaPy_data/fanuc_crx/crx10ia_l.urdf
ManipulaPy/ManipulaPy_data/fanuc_crx/crx20ia_l.urdf
ManipulaPy/ManipulaPy_data/fanuc_crx/crx30ia.urdf
ManipulaPy/ManipulaPy_data/fanuc_crx/crx5ia.urdf
ManipulaPy/ManipulaPy_data/franka_panda/panda.urdf
ManipulaPy/ManipulaPy_data/kinova/gen3/gen3.urdf
ManipulaPy/ManipulaPy_data/kinova/gen3/gen3_v12.urdf
ManipulaPy/ManipulaPy_data/kinova/jaco/jaco_6dof.urdf
ManipulaPy/ManipulaPy_data/kinova/jaco/jaco_7dof.urdf
ManipulaPy/ManipulaPy_data/kuka_iiwa/iiwa14/iiwa14.urdf
ManipulaPy/ManipulaPy_data/kuka_iiwa/iiwa14/lbr_iiwa_14_r820.urdf
ManipulaPy/ManipulaPy_data/kuka_iiwa/iiwa7/iiwa7.urdf
ManipulaPy/ManipulaPy_data/robotiq/robotiq_2f_140.urdf
ManipulaPy/ManipulaPy_data/robotiq/robotiq_2f_85.urdf
ManipulaPy/ManipulaPy_data/universal_robots/ur10/ur10.urdf
ManipulaPy/ManipulaPy_data/universal_robots/ur10e/ur10e.urdf
ManipulaPy/ManipulaPy_data/universal_robots/ur16e/ur16e.urdf
ManipulaPy/ManipulaPy_data/universal_robots/ur3/ur3.urdf
ManipulaPy/ManipulaPy_data/universal_robots/ur3e/ur3e.urdf
ManipulaPy/ManipulaPy_data/universal_robots/ur5/ur5.urdf
ManipulaPy/ManipulaPy_data/universal_robots/ur5e/ur5e.urdf
ManipulaPy/ManipulaPy_data/ur5/__init__.py
ManipulaPy/ManipulaPy_data/xarm/__init__.py
ManipulaPy/ManipulaPy_data/xarm/xarm6_robot.urdf
ManipulaPy/ManipulaPy_data/xarm/xarm6_robot_white.urdf
manipulapy-1.3.0.dist-info/licenses/LICENSE.md
manipulapy-1.3.0.dist-info/METADATA
manipulapy-1.3.0.dist-info/WHEEL
manipulapy-1.3.0.dist-info/top_level.txt
manipulapy-1.3.0.dist-info/RECORD
