Metadata-Version: 2.4
Name: ManipulaPy
Version: 1.3.0
Summary: A comprehensive Python package for robotic manipulator analysis and control
Home-page: https://github.com/boelnasr/ManipulaPy
Author: Mohamed Aboelnasr
Author-email: Mohamed Aboelnasr <aboelnasr1997@gmail.com>
License: AGPL-3.0-or-later
Project-URL: Homepage, https://github.com/boelnasr/ManipulaPy
Project-URL: Documentation, https://manipulapy.readthedocs.io/
Project-URL: Repository, https://github.com/boelnasr/ManipulaPy.git
Project-URL: Bug Tracker, https://github.com/boelnasr/ManipulaPy/issues
Project-URL: Changelog, https://github.com/boelnasr/ManipulaPy/blob/main/CHANGELOG.md
Project-URL: Funding, https://github.com/sponsors/boelnasr
Keywords: robotics,kinematics,dynamics,trajectory-planning,simulation,cuda,computer-vision,control-systems,manipulator
Platform: any
Classifier: Development Status :: 4 - Beta
Classifier: Intended Audience :: Science/Research
Classifier: Programming Language :: Python :: 3
Classifier: Programming Language :: Python :: 3.8
Classifier: Programming Language :: Python :: 3.9
Classifier: Programming Language :: Python :: 3.10
Classifier: Programming Language :: Python :: 3.11
Classifier: Topic :: Scientific/Engineering :: Artificial Intelligence
Classifier: Topic :: Scientific/Engineering :: Physics
Classifier: Topic :: Software Development :: Libraries :: Python Modules
Classifier: Operating System :: OS Independent
Classifier: Intended Audience :: Developers
Classifier: Intended Audience :: Education
Requires-Python: >=3.8
License-File: LICENSE.md
Requires-Dist: numpy<3.0,>=1.19.2
Requires-Dist: scipy>=1.5.2
Requires-Dist: matplotlib>=3.3
Requires-Dist: numba>=0.55
Requires-Dist: pybullet>=3.0.6
Requires-Dist: trimesh>=3.9.14
Requires-Dist: torch>=1.8.0
Requires-Dist: scikit-learn>=1.0
Requires-Dist: opencv-python>=4.5
Requires-Dist: ultralytics>=8.0
Requires-Dist: pillow>=8.0.0
Requires-Dist: cupy-cuda11x>=10.0.0; sys_platform != "darwin"
Provides-Extra: minimal
Requires-Dist: numpy<3.0,>=1.19.2; extra == "minimal"
Requires-Dist: scipy>=1.5.2; extra == "minimal"
Requires-Dist: matplotlib>=3.3; extra == "minimal"
Requires-Dist: numba>=0.55; extra == "minimal"
Requires-Dist: pybullet>=3.0.6; extra == "minimal"
Provides-Extra: urdf-legacy
Requires-Dist: urchin>=0.0.27; extra == "urdf-legacy"
Requires-Dist: numpy<2.0,>=1.19.2; extra == "urdf-legacy"
Provides-Extra: gpu-cuda12
Requires-Dist: cupy-cuda12x>=12.0.0; extra == "gpu-cuda12"
Provides-Extra: gpu-rocm
Requires-Dist: cupy-rocm-4-3>=10.0.0; extra == "gpu-rocm"
Provides-Extra: gpu-pycuda
Requires-Dist: pycuda>=2021.1; extra == "gpu-pycuda"
Provides-Extra: vision-headless
Requires-Dist: opencv-python-headless>=4.5; extra == "vision-headless"
Requires-Dist: ultralytics>=8.0; extra == "vision-headless"
Requires-Dist: pillow>=8.0.0; extra == "vision-headless"
Provides-Extra: dev
Requires-Dist: pytest>=6.0.0; extra == "dev"
Requires-Dist: pytest-cov>=3.0.0; extra == "dev"
Requires-Dist: pytest-mock>=3.6.0; extra == "dev"
Requires-Dist: pytest-xvfb>=2.0.0; extra == "dev"
Requires-Dist: pytest-timeout>=2.1.0; extra == "dev"
Requires-Dist: pytest-benchmark>=4.0.0; extra == "dev"
Requires-Dist: coverage[toml]>=6.0.0; extra == "dev"
Requires-Dist: black>=22.0.0; extra == "dev"
Requires-Dist: flake8>=4.0.0; extra == "dev"
Requires-Dist: isort>=5.10.0; extra == "dev"
Requires-Dist: mypy>=0.950; extra == "dev"
Requires-Dist: pre-commit>=2.15.0; extra == "dev"
Requires-Dist: tox>=4.0.0; extra == "dev"
Provides-Extra: docs
Requires-Dist: sphinx>=4.0.0; extra == "docs"
Requires-Dist: sphinx-rtd-theme>=1.0.0; extra == "docs"
Requires-Dist: myst-parser>=0.15.0; extra == "docs"
Requires-Dist: sphinx-autodoc-typehints>=1.12.0; extra == "docs"
Requires-Dist: nbsphinx>=0.8.0; extra == "docs"
Requires-Dist: jupyter>=1.0.0; extra == "docs"
Provides-Extra: ci
Requires-Dist: pytest>=6.0.0; extra == "ci"
Requires-Dist: pytest-cov>=3.0.0; extra == "ci"
Requires-Dist: pytest-mock>=3.6.0; extra == "ci"
Requires-Dist: pytest-xvfb>=2.0.0; extra == "ci"
Requires-Dist: pytest-timeout>=2.1.0; extra == "ci"
Requires-Dist: coverage[toml]>=6.0.0; extra == "ci"
Requires-Dist: opencv-python-headless>=4.5; extra == "ci"
Requires-Dist: tomli>=1.2.0; python_version < "3.11" and extra == "ci"
Provides-Extra: test-minimal
Requires-Dist: ManipulaPy[dev,minimal]; extra == "test-minimal"
Provides-Extra: test-full
Requires-Dist: ManipulaPy[dev]; extra == "test-full"
Provides-Extra: test-ci
Requires-Dist: ManipulaPy[ci,vision-headless]; extra == "test-ci"
Dynamic: author
Dynamic: home-page
Dynamic: license-file
Dynamic: platform
Dynamic: requires-python
